mipcandy_bundles/__init__.py
mipcandy_bundles/cmunext/__init__.py
mipcandy_bundles/cmunext/cmunext.py
mipcandy_bundles/cmunext/cmunext_predictor.py
mipcandy_bundles/cmunext/cmunext_trainer.py
mipcandy_bundles/mednext/__init__.py
mipcandy_bundles/mednext/mednext.py
mipcandy_bundles/mednext/mednext_predictor.py
mipcandy_bundles/mednext/mednext_trainer.py
mipcandy_bundles/unet/__init__.py
mipcandy_bundles/unet/unet.py
mipcandy_bundles/unet/unet_predictor.py
mipcandy_bundles/unet/unet_trainer.py
mipcandy_bundles/unetpp/unetpp.py
mipcandy_bundles/unetpp/unetpp_predictor.py
mipcandy_bundles/unetpp/unetpp_trainer.py
mipcandy_bundles/unetr/__init__.py
mipcandy_bundles/unetr/unetr.py
mipcandy_bundles/unetr/unetr_predictor.py
mipcandy_bundles/unetr/unetr_trainer.py
mipcandy_bundles-0.1.0.dist-info/METADATA
mipcandy_bundles-0.1.0.dist-info/WHEEL
mipcandy_bundles-0.1.0.dist-info/licenses/LICENSE
mipcandy_bundles-0.1.0.dist-info/RECORD
