Metadata-Version: 2.4
Name: mipcandy-bundles
Version: 0.1.0
Summary: Bundles for MIP Candy
Project-URL: Homepage, https://mipcandy.projectneura.org
Project-URL: Documentation, https://mipcandy-docs.projectneura.org/bundles
Project-URL: Repository, https://github.com/ProjectNeura/mipcandy-bundles
Author-email: Project Neura <central@projectneura.org>
License-Expression: Apache-2.0
License-File: LICENSE
Requires-Python: >=3.12
Requires-Dist: mipcandy
